not_much_fire/cache.py
not_much_fire/cli.py
not_much_fire/database.py
not_much_fire/notifier.py
not_much_fire-0.1.2.dist-info/entry_points.txt
not_much_fire-0.1.2.dist-info/WHEEL
not_much_fire-0.1.2.dist-info/METADATA
not_much_fire-0.1.2.dist-info/RECORD
